swarmauri_tool_containerfeedchars/ContainerFeedCharsTool.py
swarmauri_tool_containerfeedchars/__init__.py
swarmauri_tool_containerfeedchars-0.7.5.dist-info/LICENSE
swarmauri_tool_containerfeedchars-0.7.5.dist-info/METADATA
swarmauri_tool_containerfeedchars-0.7.5.dist-info/WHEEL
swarmauri_tool_containerfeedchars-0.7.5.dist-info/entry_points.txt
swarmauri_tool_containerfeedchars-0.7.5.dist-info/RECORD
